labii_sdk/__init__.py
labii_sdk/api_client.py
labii_sdk/sdk.py
labii_sdk-1.13.14.dist-info/LICENSE
labii_sdk-1.13.14.dist-info/METADATA
labii_sdk-1.13.14.dist-info/WHEEL
labii_sdk-1.13.14.dist-info/top_level.txt
labii_sdk-1.13.14.dist-info/RECORD
