Metadata-Version: 2.1
Name: labii-sdk
Version: 1.13.14
Summary: An SDK for the Labii ELN & LIMS platform (https://www.labii.com) that provides interaction with the Labii API.
Home-page: https://gitlab.com/labii-dev/labii-sdk-python
Author: Labii Inc.
Author-email: developer@labii.com
License: GNU GPLv3
Project-URL: Bug Tracker, https://gitlab.com/labii-dev/labii-sdk-python/-/issues
Requires-Python: >=3.8
License-File: LICENSE
Requires-Dist: requests>=2.27.1
Requires-Dist: boto3>=1.20.38
